LICENSE.md
mysoc_dataset/__init__.py
mysoc_dataset/__main__.py
mysoc_dataset/dataset.py
mysoc_dataset/py.typed
mysoc_dataset-0.3.0.dist-info/METADATA
mysoc_dataset-0.3.0.dist-info/entry_points.txt
mysoc_dataset-0.3.0.dist-info/WHEEL
mysoc_dataset-0.3.0.dist-info/LICENSE.md
mysoc_dataset-0.3.0.dist-info/RECORD
