Metadata-Version: 2.1
Name: mysoc-dataset
Version: 0.3.0
Summary: Tool to download mySociety datasets
Home-page: https://github.com/mysociety/mysoc-dataset
License: MIT
Author: Alex Parsons
Author-email: alex.parsons@mysociety.org
Requires-Python: >=3.7.1,<4.0.0
Classifier: License :: OSI Approved :: MIT License
Classifier: Programming Language :: Python :: 3
Classifier: Programming Language :: Python :: 3.8
Classifier: Programming Language :: Python :: 3.9
Classifier: Programming Language :: Python :: 3.10
Classifier: Programming Language :: Python :: 3.11
Requires-Dist: pandas (==1.3.5) ; python_version < "3.8"
Requires-Dist: pandas (>=1.3.5) ; python_version >= "3.8"
Requires-Dist: rich (>=12.5.1,<13.0.0)
Requires-Dist: rich-click (>=1.5.2,<2.0.0)
Project-URL: Repository, https://github.com/mysociety/mysoc-dataset
